Workbook

Sheet Hypotheses
A1: Hypothèses (cellules jaunes = à modifier). Statut supposé : micro-entreprise en franchise de TVA (TVA import non récupérable).
A3: Clé | B3: Valeur | C3: Unité | D3: Source / méthode
A4: Taux EUR/USD (BCE) | B4: 1.1225 | C4: USD pour 1 € | D4: https://www.ecb.europa.eu/stats/policy_and_exchange_rates/euro_reference_exchange_rates/html/eurofxref-graph-usd.en.html (2 oct. 2026)
A5: Prix carnet Taizhou Eego A5 (50-99 p) | B5: 3.85 | C5: USD | D5: https://www.alibaba.com/product-detail/A5-A6-Leather-Loose-Leaf-Refill_1600809910953.html
A6: Prix carnet Huizhou Weiding A5 (50-499 p) | B6: 7.22 | C6: USD | D6: https://www.alibaba.com/product-detail/Custom-Genuine-Leather-A5-Diary-Cover_1601812509058.html
A7: Fournisseur retenu (1 = Eego, 2 = Weiding) | B7: 1 | C7: choix | D7: Eego par défaut ; Weiding si l'échantillon Eego déçoit
A8: Poids facturable par carnet | B8: 0.3 | C8: kg | D8: Weiding : 0,300 kg brut (fiche) ; Eego : fiche indique 1 kg (valeur par défaut Alibaba), on retient 0,3 kg = poids volumétrique d'une boîte 21×15×5 cm (1 575 cm³ / 5 000)
A9: Fret express Chine-France | B9: 6.8 | C9: USD/kg | D9: Haut de fourchette 5,50-6,80 $/kg DHL, 3-6 jours (extrait) https://www.tonlexing.com/fr/comprendre-le-prix-de-DHL-et-le-co%C3%BBt-par-kilogramme/
A10: Frais de dossier dédouanement transporteur | B10: 20 | C10: € par envoi | D10: ESTIMATION : frais de présentation/avance de fonds facturés par les intégrateurs ; à confirmer sur la facture DHL
A11: Quantité commandée | B11: 50 | C11: pièces | D11: MOQ Eego et Weiding = 50
A12: Droit de douane 4205009000 origine CN | B12: 0.025 | C12: taux | D12: https://ec.europa.eu/taxation_customs/dds2/taric/measures.jsp?Lang=fr&Taric=4205009000&Area=CN&SimDate=20261003
A13: TVA import | B13: 0.2 | C13: taux | D13: Taux normal France ; non récupérable en franchise en base
A14: Recharge papier A5 | B14: 0.6 | C14: €/pièce | D14: ESTIMATION : à faire chiffrer par le fournisseur (inclusion non précisée sur la fiche)
A15: Film doré marquage à chaud | B15: 0.15 | C15: €/pièce | D15: ESTIMATION : rouleau ~12 € pour ~80 marquages
... A19: Shopify Payments carte UE (Basic) | B19: 0.015 | C19: taux | D19: Extrait : 1,5 % + 0,25 € (shopify.com/fr/tarifs, à revérifier)
A20: Shopify Payments fixe | B20: 0.25 | C20: €
A21: Expédition Mondial Relay Start ≤500 g (HT) | B21: 3.42 | C21: € HT | D21: https://www.mondialrelay.fr/solutions-professionnels/nos-offres-ecommercants/offre-start (lu par sous-agent)
A22: Provision retours/défauts | B22: 0.03 | C22: % du prix | D22: ESTIMATION : bien personnalisé exclu de la rétractation (art. L221-28 3° C. conso), reste la garantie de conformité
A23: Cotisations micro BIC vente | B23: 0.123 | C23: % du CA | D23: https://www.economie.gouv.fr/entreprises/gerer-sa-micro-entreprise/micro-entreprises-quel-est-le-montant-de-vos-cotisations-sociales (extrait)

Sheet Cout unitaire
A1: Poste | B1: € par carnet | C1: Formule / commentaire
A2: Produit (USD→EUR) | B2: =IF(Hypotheses!B7=1,Hypotheses!B5,Hypotheses!B6)/Hypotheses!B4 | C2: Prix Alibaba / taux BCE
A3: Fret express | B3: =Hypotheses!B8*Hypotheses!B9/Hypotheses!B4 | C3: kg × $/kg / taux
A4: Frais de dossier transporteur | B4: =Hypotheses!B10/Hypotheses!B11 | C4: par envoi / quantité
A5: Droit de douane | B5: =(B2+B3)*Hypotheses!B12 | C5: 2,5 % sur valeur CIF
A6: TVA import (non récupérable) | B6: =(B2+B3+B5)*Hypotheses!B13 | C6: 20 % sur CIF + droit
A7: Recharge papier | B7: =Hypotheses!B14
A8: Personnalisation (film doré) | B8: =Hypotheses!B15 | C8: outil amorti dans le budget, pas ici
A9: Emballage | B9: =Hypotheses!B16*1.2+Hypotheses!B17 | C9: boîte TTC + soie/sticker/carte
A10: COÛT DE REVIENT | B10: =SUM(B2:B9)
A11: Prix de vente TTC | B11: =Hypotheses!B18
A12: Ratio coût / prix | B12: =B10/B11 | C12: Contrainte : ≤ 25 %
A13: Contrainte respectée ? | B13: =IF(B12<=0.25,"OUI","NON")

Sheet Unit economics
A1: Ligne | B1: € par commande | C1: Formule / commentaire
A2: Prix TTC encaissé | B2: ='Cout unitaire'!B11 | C2: franchise TVA : pas de TVA collectée
A3: Coût de revient | B3: =-'Cout unitaire'!B10
A4: Frais Shopify Payments | B4: =-(B2*Hypotheses!B19+Hypotheses!B20)
A5: Livraison offerte (Mondial Relay Start, TTC) | B5: =-Hypotheses!B21*1.2 | C5: Colissimo domicile proposé en option payante +4,90 €
A6: Provision retours/défauts | B6: =-B2*Hypotheses!B22
A7: Cotisations sociales micro | B7: =-B2*Hypotheses!B23
A8: CONTRIBUTION AVANT PUB | B8: =SUM(B2:B7) | C8: =coût d'acquisition maximum au point mort
A9: Marge de contribution % | B9: =B8/B2
A12: Scénarios de coût d'acquisition (CPA Meta)
A13: Scénario | B13: CPA (€) | C13: Profit par commande | D13: Commandes avec 300 € de pub | E13: Profit total du test pub
A14: Optimiste | B14: 12 | C14: =$B$8-B14 | D14: =ROUNDDOWN(Budget!$B$15/B14,0) | E14: =C14*D14
A15: Central | B15: 20 | C15: =$B$8-B15 | D15: =ROUNDDOWN(Budget!$B$15/B15,0) | E15: =C15*D15
A16: Pessimiste | B16: 30 | C16: =$B$8-B16 | D16: =ROUNDDOWN(Budget!$B$15/B16,0) | E16: =C16*D16
A18: CPA maximum (point mort) | B18: =B8
A19: Panier B2B : 20 carnets avec logo à 35 € HT/u (gravure laser fablab ~1 €/u en plus) | B19: =20*(35-'Cout unitaire'!B10-1) | C19: contribution d'une commande B2B de 20 pièces, sans pub

Sheet Budget
A1: Poste | B1: Montant (€) | C1: Calcul / source
A2: Échantillons Eego + Weiding (port express inclus) | B2: =(0+25+2*30)/Hypotheses!B4 | C2: Weiding : échantillon 25 $ (fiche) ; Eego : « free samples » ; port ESTIMATION 30 $ chacun
A3: Stock 50 carnets | B3: =Hypotheses!B11*'Cout unitaire'!B2
A4: Fret express 15 kg | B4: =Hypotheses!B11*'Cout unitaire'!B3
A5: Droits + TVA import + frais de dossier | B5: =Hypotheses!B11*('Cout unitaire'!B4+'Cout unitaire'!B5+'Cout unitaire'!B6)
A6: Recharges papier | B6: =Hypotheses!B11*Hypotheses!B14
A7: Presse de marquage à chaud manuelle 110 W | B7: 89.9 | C7: https://www.decocuir.com/en/collections/presse-marquer-chaud-cuir (extrait)
A8: Alphabet laiton 26 capitales 4 mm | B8: 46.58 | C8: https://www.am-marquagecuir.com/pages/alphabets (extrait)
A9: Film doré (2 rouleaux) | B9: =Hypotheses!B11*Hypotheses!B15+5 | C9: ESTIMATION
A10: Emballages | B10: =Hypotheses!B11*'Cout unitaire'!B9
A11: Shopify Basic (offre 1 €/mois × 1 mois) | B11: 1 | C11: Offre de lancement (extrait), à revérifier
A12: Nom de domaine .fr (1 an) | B12: 12 | C12: ESTIMATION
A13: Appli personnalisation (Zepto Starter 9,99 $) | B13: =9.99/Hypotheses!B4 | C13: https://apps.shopify.com/product-personalizer (extrait) ; Judge.me, GPSReady, mentions légales : gratuits
A14: Accessoires shooting maison | B14: 20 | C14: ESTIMATION
A15: PUB TEST META (solde) | B15: =1000-SUM(B2:B14) | C15: Tout le reste du budget va à la pub
A16: TOTAL | B16: =SUM(B2:B15) | C16: doit faire 1 000 €
