Workbook

Sheet Hypotheses
A1: Hypothèses du modèle 24 mois (cellules jaunes modifiables)
A3: Taux QAR pour 1 EUR | B3: 4.086 | C3: QAR ancré à 3,64 QAR/USD ; BCE 2 oct. 2026 : 1 € = 1,1225 $ → 3,64 × 1,1225
A4: Prix moyen par clinique (ARPA, QAR/mois) | B4: 699 | C4: mix des paliers 399 / 799 / 1 490 QAR (voir spec-mvp.md)
A5: Churn mensuel | B5: 0.03 | C5: ESTIMATION SaaS PME
A6: Rendez-vous par clinique et par mois | B6: 500 | C6: ESTIMATION : 20-25 RDV/jour ouvré pour une clinique de 2-4 praticiens
A7: Messages WhatsApp par rendez-vous | B7: 2 | C7: rappel J-1 + rappel H-3
A8: Coût d'un message utility Qatar (USD) | B8: 0.02 | C8: ESTIMATION : Qatar sorti de « Rest of Middle East » au 1er juil. 2026 avec tarif plus élevé ; montant exact dans le CSV officiel Meta https://developers.facebook.com/documentation/business-messaging/whatsapp/pricing
A9: Taux USD pour 1 EUR | B9: 1.1225 | C9: BCE 2 oct. 2026
A10: Frais Stripe cartes hors EEE | B10: 0.0325 | C10: extrait : stripe.com/fr/pricing (via indy.fr)
A11: Frais Stripe conversion de devise (facturation en QAR) | B11: 0.02 | C11: extrait
A12: Frais fixe Stripe par facture (EUR) | B12: 0.25 | C12: extrait
A13: Hébergement GCP Doha + base de données (EUR/mois) | B13: 90 | C13: ESTIMATION Cloud Run + Cloud SQL plus petit palier, région me-central1
A14: Outils (abonnement Claude, domaine, e-mail) (EUR/mois) | B14: 130 | C14: ESTIMATION
... A20: Retenue à la source qatarie appliquée (0 = convention France-Qatar respectée) | B20: 0 | C20: mettre 0,05 pour le scénario défavorable (WHT 5 %)

Sheet Mensuel
A1: Modèle financier 24 mois (EUR sauf mention). M1-M2 construction ; M3 pilotes gratuits ; M4 Web Summit (31 janv.-3 fév.) puis Ramadan (≈8 fév.-9 mars 2027) ; été ralenti (juin-août) ; Ramadan 2028 ≈ fin janv.-fin fév.
A2: Ligne | B2: M1 nov. 26 | C2: M2 déc. 26 | D2: M3 janv. 27 | E2: M4 févr. 27 | F2: M5 mars 27 | G2: M6 avr. 27 | H2: M7 mai 27 | I2: M8 juin 27 | J2: M9 juil. 27 | K2: M10 août 27 | L2: M11 sept. 27 | M2: M12 oct. 27 | N2: M13 nov. 27 | O2: M14 déc. 27 | P2: M15 janv. 28 | Q2: M16 févr. 28 | R2: M17 mars 28 | S2: M18 avr. 28 | T2: M19 mai 28 | U2: M20 juin 28 | V2: M21 juil. 28 | W2: M22 août 28 | X2: M23 sept. 28 | Y2: M24 oct. 28 | Z2: TOTAL 24 mois
A3: Nouvelles cliniques payantes | B3: 0 | C3: 0 | D3: 0 | E3: 2 | F3: 2 | G3: 3 | H3: 3 | I3: 2 | J3: 1 | K3: 1 | L3: 3 | M3: 4 | N3: 4 | O3: 4 | P3: 4 | Q3: 5 | R3: 5 | S3: 5 | T3: 5 | U3: 3 | V3: 2 | W3: 3 | X3: 5 | Y3: 6 | Z3: =SUM(B3:Y3)
A4: Cliniques perdues (churn) | B4: =0 | C4: =ROUND(B5*Hypotheses!$B$5,0) | D4: =ROUND(C5*Hypotheses!$B$5,0) | E4: =ROUND(D5*Hypotheses!$B$5,0) | F4: =ROUND(E5*Hypotheses!$B$5,0) | G4: =ROUND(F5*Hypotheses!$B$5,0) | H4: =ROUND(G5*Hypotheses!$B$5,0) | I4: =ROUND(H5*Hypotheses!$B$5,0) | J4: =ROUND(I5*Hypotheses!$B$5,0) | ... Y4: =ROUND(X5*Hypotheses!$B$5,0) | Z4: =SUM(B4:Y4)
A5: Cliniques actives fin de mois | B5: =B3 | C5: =B5+C3-C4 | D5: =C5+D3-D4 | E5: =D5+E3-E4 | F5: =E5+F3-F4 | G5: =F5+G3-G4 | H5: =G5+H3-H4 | I5: =H5+I3-I4 | J5: =I5+J3-J4 | ... Y5: =X5+Y3-Y4 | Z5: =Y5
A6: Chiffre d'affaires (QAR) | B6: =B5*Hypotheses!$B$4 | C6: =C5*Hypotheses!$B$4 | D6: =D5*Hypotheses!$B$4 | E6: =E5*Hypotheses!$B$4 | F6: =F5*Hypotheses!$B$4 | G6: =G5*Hypotheses!$B$4 | H6: =H5*Hypotheses!$B$4 | I6: =I5*Hypotheses!$B$4 | ... Y6: =Y5*Hypotheses!$B$4 | Z6: =SUM(B6:Y6)
A7: Chiffre d'affaires (EUR) | B7: =B6/Hypotheses!$B$3 | C7: =C6/Hypotheses!$B$3 | D7: =D6/Hypotheses!$B$3 | E7: =E6/Hypotheses!$B$3 | F7: =F6/Hypotheses!$B$3 | G7: =G6/Hypotheses!$B$3 | H7: =H6/Hypotheses!$B$3 | I7: =I6/Hypotheses!$B$3 | ... Y7: =Y6/Hypotheses!$B$3 | Z7: =SUM(B7:Y7)
A8: Coût WhatsApp (EUR) | B8: =-B5*Hypotheses!$B$6*Hypotheses!$B$7*Hypotheses!$B$8/Hypotheses!$B$9 | C8: =-C5*Hypotheses!$B$6*Hypotheses!$B$7*Hypotheses!$B$8/Hypotheses!$B$9 | D8: =-D5*Hypotheses!$B$6*Hypotheses!$B$7*Hypotheses!$B$8/Hypotheses!$B$9 | E8: =-E5*Hypotheses!$B$6*Hypotheses!$B$7*Hypotheses!$B$8/Hypotheses!$B$9 | F8: =-F5*Hypotheses!$B$6*Hypotheses!$B$7*Hypotheses!$B$8/Hypotheses!$B$9 | G8: =-G5*Hypotheses!$B$6*Hypotheses!$B$7*Hypotheses!$B$8/Hypotheses!$B$9 | H8: =-H5*Hypotheses!$B$6*Hypotheses!$B$7*Hypotheses!$B$8/Hypotheses!$B$9 | I8: =-I5*Hypotheses!$B$6*Hypotheses!$B$7*Hypotheses!$B$8/Hypotheses!$B$9 | ... Y8: =-Y5*Hypotheses!$B$6*Hypotheses!$B$7*Hypotheses!$B$8/Hypotheses!$B$9 | Z8: =SUM(B8:Y8)
A9: Frais Stripe (EUR) | B9: =-(B7*(Hypotheses!$B$10+Hypotheses!$B$11)+B5*Hypotheses!$B$12) | C9: =-(C7*(Hypotheses!$B$10+Hypotheses!$B$11)+C5*Hypotheses!$B$12) | D9: =-(D7*(Hypotheses!$B$10+Hypotheses!$B$11)+D5*Hypotheses!$B$12) | E9: =-(E7*(Hypotheses!$B$10+Hypotheses!$B$11)+E5*Hypotheses!$B$12) | F9: =-(F7*(Hypotheses!$B$10+Hypotheses!$B$11)+F5*Hypotheses!$B$12) | G9: =-(G7*(Hypotheses!$B$10+Hypotheses!$B$11)+G5*Hypotheses!$B$12) | H9: =-(H7*(Hypotheses!$B$10+Hypotheses!$B$11)+H5*Hypotheses!$B$12) | I9: =-(I7*(Hypotheses!$B$10+Hypotheses!$B$11)+I5*Hypotheses!$B$12) | ... Y9: =-(Y7*(Hypotheses!$B$10+Hypotheses!$B$11)+Y5*Hypotheses!$B$12) | Z9: =SUM(B9:Y9)
A10: Retenue à la source (EUR) | B10: =-B7*Hypotheses!$B$20 | C10: =-C7*Hypotheses!$B$20 | D10: =-D7*Hypotheses!$B$20 | E10: =-E7*Hypotheses!$B$20 | F10: =-F7*Hypotheses!$B$20 | G10: =-G7*Hypotheses!$B$20 | H10: =-H7*Hypotheses!$B$20 | I10: =-I7*Hypotheses!$B$20 | ... Y10: =-Y7*Hypotheses!$B$20 | Z10: =SUM(B10:Y10)
A11: Marge brute (EUR) | B11: =B7+B8+B9+B10 | C11: =C7+C8+C9+C10 | D11: =D7+D8+D9+D10 | E11: =E7+E8+E9+E10 | F11: =F7+F8+F9+F10 | G11: =G7+G8+G9+G10 | H11: =H7+H8+H9+H10 | I11: =I7+I8+I9+I10 | ... Y11: =Y7+Y8+Y9+Y10 | Z11: =SUM(B11:Y11)
A12: Marge brute % | B12: =IF(B7=0,"",B11/B7) | C12: =IF(C7=0,"",C11/C7) | D12: =IF(D7=0,"",D11/D7) | E12: =IF(E7=0,"",E11/E7) | F12: =IF(F7=0,"",F11/F7) | G12: =IF(G7=0,"",G11/G7) | H12: =IF(H7=0,"",H11/H7) | I12: =IF(I7=0,"",I11/I7) | ... Y12: =IF(Y7=0,"",Y11/Y7)
A13: Hébergement | B13: =-Hypotheses!$B$13 | C13: =-Hypotheses!$B$13 | D13: =-Hypotheses!$B$13 | E13: =-Hypotheses!$B$13 | F13: =-Hypotheses!$B$13 | G13: =-Hypotheses!$B$13 | H13: =-Hypotheses!$B$13 | I13: =-Hypotheses!$B$13 | ... Y13: =-Hypotheses!$B$13 | Z13: =SUM(B13:Y13)
A14: Outils | B14: =-Hypotheses!$B$14 | C14: =-Hypotheses!$B$14 | D14: =-Hypotheses!$B$14 | E14: =-Hypotheses!$B$14 | F14: =-Hypotheses!$B$14 | G14: =-Hypotheses!$B$14 | H14: =-Hypotheses!$B$14 | I14: =-Hypotheses!$B$14 | ... Y14: =-Hypotheses!$B$14 | Z14: =SUM(B14:Y14)
A15: Comptable + assurance | B15: =-Hypotheses!$B$15 | C15: =-Hypotheses!$B$15 | D15: =-Hypotheses!$B$15 | E15: =-Hypotheses!$B$15 | F15: =-Hypotheses!$B$15 | G15: =-Hypotheses!$B$15 | H15: =-Hypotheses!$B$15 | I15: =-Hypotheses!$B$15 | ... Y15: =-Hypotheses!$B$15 | Z15: =SUM(B15:Y15)
A16: Marketing | B16: =0 | C16: =0 | D16: =-Hypotheses!$B$16 | E16: =-Hypotheses!$B$16 | F16: =-Hypotheses!$B$16 | G16: =-Hypotheses!$B$16 | H16: =-Hypotheses!$B$16 | I16: =-Hypotheses!$B$16 | J16: =-Hypotheses!$B$16 | K16: =-Hypotheses!$B$16 | ... Y16: =-Hypotheses!$B$16 | Z16: =SUM(B16:Y16)
A17: Juridique | B17: =0 | C17: =-Hypotheses!$B$17 | D17: =0 | E17: =0 | F17: =0 | G17: =0 | H17: =0 | I17: =0 | J17: =0 | K17: =0 | ... Y17: =0 | Z17: =SUM(B17:Y17)
A18: Voyages | B18: =0 | C18: =0 | D18: =0 | E18: =-Hypotheses!$B$18 | F18: =0 | G18: =0 | H18: =0 | I18: =0 | J18: =0 | K18: =0 | L18: =0 | M18: =0 | ... P18: =0 | Q18: =-Hypotheses!$B$19 | R18: =0 | S18: =0 | T18: =0 | U18: =0 | V18: =0 | W18: =0 | X18: =0 | Y18: =0 | Z18: =SUM(B18:Y18)
A19: Total charges fixes | B19: =SUM(B13:B18) | C19: =SUM(C13:C18) | D19: =SUM(D13:D18) | E19: =SUM(E13:E18) | F19: =SUM(F13:F18) | G19: =SUM(G13:G18) | H19: =SUM(H13:H18) | I19: =SUM(I13:I18) | ... Y19: =SUM(Y13:Y18) | Z19: =SUM(B19:Y19)
A20: Résultat mensuel (EUR) | B20: =B11+B19 | C20: =C11+C19 | D20: =D11+D19 | E20: =E11+E19 | F20: =F11+F19 | G20: =G11+G19 | H20: =H11+H19 | I20: =I11+I19 | ... Y20: =Y11+Y19 | Z20: =SUM(B20:Y20)
A21: Trésorerie cumulée (EUR) | B21: =B20 | C21: =B21+C20 | D21: =C21+D20 | E21: =D21+E20 | F21: =E21+F20 | G21: =F21+G20 | H21: =G21+H20 | I21: =H21+I20 | J21: =I21+J20 | ... Y21: =X21+Y20 | Z21: =Y21
A23: Besoin de financement maximal (creux de trésorerie) | B23: =MIN(B21:Y21)
A24: Premier mois à résultat positif | B24: =IFERROR(INDEX(B2:Y2,MATCH(TRUE,INDEX(B20:Y20>0,0),0)),"aucun")
A25: MRR fin M24 (EUR) | B25: =Y7
A26: Seuil de rentabilité (cliniques) = charges fixes M24 / marge brute par clinique | B26: =-Y19/(Y11/Y5)

Sheet Risques
A1: Risque | B1: Probabilité | C1: Impact | D1: Solution | E1: Coût de la solution
A2: Données de santé = « nature spéciale » (PDPPL art. 16) : autorisation préalable requise | B2: Forte | C2: Fort | D2: La clinique reste responsable de traitement ; contrat de sous-traitance ; données minimales (prénom, téléphone, date, sans motif médical) ; hébergement GCP Doha ; suppression à J+30 ; vérifier avec un avocat qatari si l'autorisation de la clinique couvre le sous-traitant | E2: ~1 500 € de conseil (budget Juridique M2)
A3: Cartes NAPS/Himyan non acceptées par Stripe | B3: Moyenne | C3: Moyen | D3: Facturation B2B : cartes Visa/Mastercard d'entreprise ou virement SWIFT annuel ; à terme passerelle locale (Dibsy, récurrent) via une entité au Qatar | E3: 0 € puis frais de licence QFC 500 $ + 5 000 $/an si entité
A4: Retenue à la source de 5 % sur services | B4: Moyenne | C4: Faible | D4: Certificat de résidence fiscale (formulaire 5000) + régime « Trusted Entity » ; sinon demande de remboursement à la GTA | E4: 0 € (scénario 5 % testable dans Hypotheses B20)
A5: Concurrence : HeliumDoc, Tabeebak, healthandmedical.qa, outils WhatsApp génériques | B5: Forte | C5: Moyen | D5: Se positionner comme outil de la clinique (pas une place de marché qui capte le patient) ; arabe natif ; liste d'attente ; prix fixe | E5: 0 €
A6: Tarif WhatsApp Qatar plus élevé que prévu | B6: Moyenne | C6: Faible | D6: Lire le CSV officiel Meta ; répercuter au-delà d'un quota de messages ; un seul rappel J-1 si nécessaire | E6: 0 €
A7: Vente à distance sans présence locale = méfiance | B7: Forte | C7: Fort | D7: Pilote gratuit 30 jours ; démo vidéo en arabe ; visite au Web Summit Qatar (fév. 2027) ; partenaire revendeur local | E7: 2 200 € (voyage M4)
A8: Changement de politique Meta (templates refusés, numéro bloqué) | B8: Faible | C8: Fort | D8: Templates « utility » sobres validés à l'avance ; repli SMS (fournisseur local) ; un numéro par clinique | E8: ~0,05 $/SMS (ESTIMATION) en repli
